swh/alter/__init__.py
swh/alter/bech32.py
swh/alter/cli.py
swh/alter/inventory.py
swh/alter/mirror_notification_watcher.py
swh/alter/notifications.py
swh/alter/operations.py
swh/alter/progressbar.py
swh/alter/py.typed
swh/alter/recovery_bundle.py
swh/alter/removable.py
swh/alter/subgraph.py
swh/alter/utils.py
swh/alter/tests/__init__.py
swh/alter/tests/conftest.py
swh/alter/tests/test_cli.py
swh/alter/tests/test_cli_notify.py
swh/alter/tests/test_inventory.py
swh/alter/tests/test_mirror_notification_watcher.py
swh/alter/tests/test_notifications.py
swh/alter/tests/test_operations.py
swh/alter/tests/test_recovery_bundle.py
swh/alter/tests/test_removable.py
swh/alter/tests/test_subgraph.py
swh/alter/tests/test_utils.py
swh/alter/tests/fixtures/complete-manifest.swh-recovery-bundle
swh/alter/tests/fixtures/decryption-key-recovery.swh-recovery-bundle
swh/alter/tests/fixtures/no-yubikeys.swh-recovery-bundle
swh/alter/tests/fixtures/sample-version-1.swh-recovery-bundle
swh/alter/tests/fixtures/sample-version-2.swh-recovery-bundle
swh/alter/tests/fixtures/sample-version-3.swh-recovery-bundle
swh_alter-1.4.0.dist-info/licenses/AUTHORS
swh_alter-1.4.0.dist-info/licenses/LICENSE
swh_alter-1.4.0.dist-info/METADATA
swh_alter-1.4.0.dist-info/WHEEL
swh_alter-1.4.0.dist-info/entry_points.txt
swh_alter-1.4.0.dist-info/top_level.txt
swh_alter-1.4.0.dist-info/RECORD
