Metadata-Version: 2.4
Name: swh.alter
Version: 1.4.0
Summary: Software Heritage archive modification tools
Author-email: Software Heritage developers <swh-devel@inria.fr>
Project-URL: Homepage, https://gitlab.softwareheritage.org/swh/devel/swh-alter
Project-URL: Bug Reports, https://gitlab.softwareheritage.org/swh/devel/swh-alter/-/issues
Project-URL: Funding, https://www.softwareheritage.org/donate
Project-URL: Documentation, https://docs.softwareheritage.org/devel/swh-alter/
Project-URL: Source, https://gitlab.softwareheritage.org/swh/devel/swh-alter.git
Classifier: Programming Language :: Python :: 3
Classifier: Intended Audience :: Developers
Classifier: License :: OSI Approved :: GNU General Public License v3 (GPLv3)
Classifier: Operating System :: OS Independent
Classifier: Development Status :: 3 - Alpha
Requires-Python: >=3.10
License-File: LICENSE
License-File: AUTHORS
Requires-Dist: attrs
Requires-Dist: click
Requires-Dist: humanize
Requires-Dist: igraph
Requires-Dist: pyyaml
Requires-Dist: shamir-mnemonic
Requires-Dist: tabulate
Requires-Dist: typing_extensions
Requires-Dist: swh.core[http]>=4.1.0
Requires-Dist: swh.graph>=3.1
Requires-Dist: swh.model>=6.13.0
Requires-Dist: swh.search>=0.19
Requires-Dist: swh.storage>=3.0.0
Requires-Dist: swh.objstorage
Provides-Extra: testing
Requires-Dist: attrs; extra == "testing"
Requires-Dist: click; extra == "testing"
Requires-Dist: humanize; extra == "testing"
Requires-Dist: igraph; extra == "testing"
Requires-Dist: pyyaml; extra == "testing"
Requires-Dist: shamir-mnemonic; extra == "testing"
Requires-Dist: tabulate; extra == "testing"
Requires-Dist: typing_extensions; extra == "testing"
Requires-Dist: swh.core[http]>=4.1.0; extra == "testing"
Requires-Dist: swh.graph>=3.1; extra == "testing"
Requires-Dist: swh.model>=6.13.0; extra == "testing"
Requires-Dist: swh.search>=0.19; extra == "testing"
Requires-Dist: swh.storage>=3.0.0; extra == "testing"
Requires-Dist: swh.objstorage; extra == "testing"
Requires-Dist: pytest>=8.1; extra == "testing"
Requires-Dist: pytest-smtpd; extra == "testing"
Requires-Dist: swh.core[testing]>=4.0.0; extra == "testing"
Requires-Dist: swh.graph[testing]; extra == "testing"
Requires-Dist: swh.storage[testing]>=3.0.0; extra == "testing"
Requires-Dist: types-pyyaml; extra == "testing"
Requires-Dist: types-tabulate; extra == "testing"
Dynamic: license-file
